isalive.py
isalive-0.1.1.dist-info/LICENSE
isalive-0.1.1.dist-info/METADATA
isalive-0.1.1.dist-info/WHEEL
isalive-0.1.1.dist-info/entry_points.txt
isalive-0.1.1.dist-info/RECORD
